[
	{
		"name": "Industrialists",
		"leaderName": "CEO",
		"adjective": ["Corporate"],
		"startBias": ["Grassland"],
		"preferredVictoryType": "Scientific",
		
		"startIntroPart1": "This will do!",
		"startIntroPart2": "",
		
		"declaringWar": "Resistance is futile! Prepare to be assimilated!",
		"attacked": "You want to play? Very funny!",
		"defeated": "How is it possible?",
		"introduction": "You are not worthy of our attention.",
		
		"neutralHello": "How are you doing?",
		"neutralLetsHearIt": ["Go on.","What do you say?","You may begin."],
		"neutralNo": ["We absolutely refuse.","No!","I refuse."],
		"neutralYes": ["Very good.","Of course, yes.","That is very good."],

		"hateHello": "What do you want now?",
		"hateLetsHearIt": ["Speak!","What do you say?","Go on."],
		"hateNo": ["That is not possible!","We are not agreeing to that!","I beg your pardon?"],
		"hateYes": ["That is fine.","That is good enough.","Very well..."],
		
		"afterPeace": "Very well, all that fighting was getting boring anyway.",
		"tradeRequest": "We bestow you the honor of this trade offer.",

		"outerColor": [16,16,16],
		"innerColor": [255,200,200],
		"uniqueName": "Industrial Might",
		"uniques": ["[+1 Gold] from every [Road]", "[+1 Production] from every [Road]", "[+1 Food] from every [Road]",
			    "[+3 Gold] from every [Railroad]", "[+3 Production] from every [Railroad]", "[+3 Food] from every [Railroad]",
			    "[+2 Gold] from every [Manufactory]", "[+3 Production] from every [Manufactory]", "[+3 Happiness] from every [Manufactory]",
			    "Free [Great Engineer] appears <upon discovering [Engineering] technology>", "Free [Great Engineer] appears <upon discovering [Construction] technology>",
			    "Free [Great Engineer] appears <upon discovering [Iron Working] technology>", "Free [Great Engineer] appears <upon discovering [Steel] technology>"],
		"cities": ["HQ", "Secondary Office", "Outward Command", "Outpost 1", "Outpost 2", "Outpost 3", "Outpost 4"]
	}
]
